{
  "generatedAt": "2026-05-23T19:37:48.406Z",
  "totals": {
    "files": 35,
    "citations": 0,
    "unresolved": 33,
    "averageScore": 71
  },
  "articles": [
    {
      "file": "src/content/blog/article-01-personal-finance-for-beginners.md",
      "words": 5988,
      "citationCount": 0,
      "citationDensityPer1000Words": 0,
      "unresolved": [],
      "unknown": [],
      "sourceIds": [],
      "categories": [],
      "score": 77
    },
    {
      "file": "src/content/blog/article-02-how-to-budget-money.md",
      "words": 5170,
      "citationCount": 0,
      "citationDensityPer1000Words": 0,
      "unresolved": [],
      "unknown": [],
      "sourceIds": [],
      "categories": [],
      "score": 77
    },
    {
      "file": "src/content/blog/article-03-how-to-save-money-emergency-fund.md",
      "words": 5255,
      "citationCount": 0,
      "citationDensityPer1000Words": 0,
      "unresolved": [],
      "unknown": [],
      "sourceIds": [],
      "categories": [],
      "score": 77
    },
    {
      "file": "src/content/blog/article-04-how-to-build-credit.md",
      "words": 4981,
      "citationCount": 0,
      "citationDensityPer1000Words": 0,
      "unresolved": [],
      "unknown": [],
      "sourceIds": [],
      "categories": [],
      "score": 77
    },
    {
      "file": "src/content/blog/article-06-index-funds-vs-etfs.md",
      "words": 5463,
      "citationCount": 0,
      "citationDensityPer1000Words": 0,
      "unresolved": [],
      "unknown": [],
      "sourceIds": [],
      "categories": [],
      "score": 77
    },
    {
      "file": "src/content/blog/article-07-how-to-build-business-credit.md",
      "words": 5057,
      "citationCount": 0,
      "citationDensityPer1000Words": 0,
      "unresolved": [],
      "unknown": [],
      "sourceIds": [],
      "categories": [],
      "score": 77
    },
    {
      "file": "src/content/blog/article-08-best-business-credit-cards-new-business.md",
      "words": 4980,
      "citationCount": 0,
      "citationDensityPer1000Words": 0,
      "unresolved": [],
      "unknown": [],
      "sourceIds": [],
      "categories": [],
      "score": 77
    },
    {
      "file": "src/content/blog/article-09-financial-freedom-roadmap.md",
      "words": 5237,
      "citationCount": 0,
      "citationDensityPer1000Words": 0,
      "unresolved": [],
      "unknown": [],
      "sourceIds": [],
      "categories": [],
      "score": 77
    },
    {
      "file": "src/content/blog/article-10-ai-finance-tools.md",
      "words": 5602,
      "citationCount": 0,
      "citationDensityPer1000Words": 0,
      "unresolved": [],
      "unknown": [],
      "sourceIds": [],
      "categories": [],
      "score": 77
    },
    {
      "file": "src/content/blog/article-11-ai-seo-tools-small-business.md",
      "words": 4122,
      "citationCount": 0,
      "citationDensityPer1000Words": 0,
      "unresolved": [],
      "unknown": [],
      "sourceIds": [],
      "categories": [],
      "score": 77
    },
    {
      "file": "src/content/blog/article-12-shopify-seo-guide.md",
      "words": 6018,
      "citationCount": 0,
      "citationDensityPer1000Words": 0,
      "unresolved": [],
      "unknown": [],
      "sourceIds": [],
      "categories": [],
      "score": 77
    },
    {
      "file": "src/content/blog/article-13-ecommerce-seo-strategy.md",
      "words": 6726,
      "citationCount": 0,
      "citationDensityPer1000Words": 0,
      "unresolved": [],
      "unknown": [],
      "sourceIds": [],
      "categories": [],
      "score": 77
    },
    {
      "file": "src/content/blog/average-stock-market-return.md",
      "words": 2948,
      "citationCount": 0,
      "citationDensityPer1000Words": 0,
      "unresolved": [],
      "unknown": [],
      "sourceIds": [],
      "categories": [],
      "score": 77
    },
    {
      "file": "src/content/blog/case-studies/blackwater-seo-growth.md",
      "words": 975,
      "citationCount": 0,
      "citationDensityPer1000Words": 0,
      "unresolved": [],
      "unknown": [],
      "sourceIds": [],
      "categories": [],
      "score": 100
    },
    {
      "file": "src/content/blog/compound-01-how-compound-interest-works.md",
      "words": 4409,
      "citationCount": 0,
      "citationDensityPer1000Words": 0,
      "unresolved": [],
      "unknown": [],
      "sourceIds": [],
      "categories": [],
      "score": 77
    },
    {
      "file": "src/content/blog/compound-02-compound-interest-formula.md",
      "words": 3385,
      "citationCount": 0,
      "citationDensityPer1000Words": 0,
      "unresolved": [],
      "unknown": [],
      "sourceIds": [],
      "categories": [],
      "score": 77
    },
    {
      "file": "src/content/blog/compound-03-daily-vs-monthly-compound-interest.md",
      "words": 2858,
      "citationCount": 0,
      "citationDensityPer1000Words": 0,
      "unresolved": [],
      "unknown": [],
      "sourceIds": [],
      "categories": [],
      "score": 77
    },
    {
      "file": "src/content/blog/compound-04-compound-interest-examples.md",
      "words": 2951,
      "citationCount": 0,
      "citationDensityPer1000Words": 0,
      "unresolved": [],
      "unknown": [],
      "sourceIds": [],
      "categories": [],
      "score": 77
    },
    {
      "file": "src/content/blog/compound-05-how-much-will-500-a-month-grow.md",
      "words": 2520,
      "citationCount": 0,
      "citationDensityPer1000Words": 0,
      "unresolved": [],
      "unknown": [],
      "sourceIds": [],
      "categories": [],
      "score": 77
    },
    {
      "file": "src/content/blog/compound-06-how-long-to-reach-1-million-investing.md",
      "words": 2940,
      "citationCount": 0,
      "citationDensityPer1000Words": 0,
      "unresolved": [],
      "unknown": [],
      "sourceIds": [],
      "categories": [],
      "score": 77
    },
    {
      "file": "src/content/blog/compound-07-best-compound-interest-investments.md",
      "words": 3824,
      "citationCount": 0,
      "citationDensityPer1000Words": 0,
      "unresolved": [],
      "unknown": [],
      "sourceIds": [],
      "categories": [],
      "score": 77
    },
    {
      "file": "src/content/blog/compound-08-compound-interest-canada.md",
      "words": 3962,
      "citationCount": 0,
      "citationDensityPer1000Words": 0,
      "unresolved": [],
      "unknown": [],
      "sourceIds": [],
      "categories": [],
      "score": 77
    },
    {
      "file": "src/content/blog/compound-09-how-much-will-100-a-month-grow.md",
      "words": 2743,
      "citationCount": 0,
      "citationDensityPer1000Words": 0,
      "unresolved": [],
      "unknown": [],
      "sourceIds": [],
      "categories": [],
      "score": 77
    },
    {
      "file": "src/content/blog/compound-10-compound-interest-savings-account.md",
      "words": 3489,
      "citationCount": 0,
      "citationDensityPer1000Words": 0,
      "unresolved": [],
      "unknown": [],
      "sourceIds": [],
      "categories": [],
      "score": 77
    },
    {
      "file": "src/content/blog/how-to-start-investing.md",
      "words": 4063,
      "citationCount": 0,
      "citationDensityPer1000Words": 0,
      "unresolved": [],
      "unknown": [],
      "sourceIds": [],
      "categories": [],
      "score": 77
    },
    {
      "file": "src/content/blog/index-fund-investing.md",
      "words": 4021,
      "citationCount": 0,
      "citationDensityPer1000Words": 0,
      "unresolved": [],
      "unknown": [],
      "sourceIds": [],
      "categories": [],
      "score": 77
    },
    {
      "file": "src/content/blog/investing-for-beginners.md",
      "words": 4719,
      "citationCount": 0,
      "citationDensityPer1000Words": 0,
      "unresolved": [],
      "unknown": [],
      "sourceIds": [],
      "categories": [],
      "score": 77
    },
    {
      "file": "src/content/blog/investment-calculator-guide.md",
      "words": 3218,
      "citationCount": 0,
      "citationDensityPer1000Words": 0,
      "unresolved": [],
      "unknown": [],
      "sourceIds": [],
      "categories": [],
      "score": 77
    },
    {
      "file": "blog/html/article-html-01-how-to-build-an-ecommerce-brand.html",
      "words": 9941,
      "citationCount": 0,
      "citationDensityPer1000Words": 0,
      "unresolved": [
        "[SOURCE NEEDED for industry benchmarks]",
        "[SOURCE NEEDED]",
        "[SOURCE NEEDED]",
        "[SOURCE NEEDED]",
        "[SOURCE NEEDED]",
        "[SOURCE NEEDED]",
        "[SOURCE NEEDED]",
        "[SOURCE NEEDED]",
        "[SOURCE NEEDED]",
        "[SOURCE NEEDED]",
        "[SOURCE NEEDED]",
        "[SOURCE NEEDED]",
        "[SOURCE NEEDED — consult a qualified accountant]",
        "[SOURCE NEEDED]",
        "[SOURCE NEEDED]",
        "[SOURCE NEEDED for industry benchmarks]"
      ],
      "unknown": [],
      "sourceIds": [],
      "categories": [],
      "score": 0
    },
    {
      "file": "blog/html/article-html-02-shopify-seo-strategy.html",
      "words": 9772,
      "citationCount": 0,
      "citationDensityPer1000Words": 0,
      "unresolved": [
        "[SOURCE NEEDED]"
      ],
      "unknown": [],
      "sourceIds": [],
      "categories": [],
      "score": 62
    },
    {
      "file": "blog/html/article-html-03-niche-ecommerce-topical-authority.html",
      "words": 8617,
      "citationCount": 0,
      "citationDensityPer1000Words": 0,
      "unresolved": [],
      "unknown": [],
      "sourceIds": [],
      "categories": [],
      "score": 77
    },
    {
      "file": "blog/html/article-html-04-blackwater-aquatics-case-study.html",
      "words": 8487,
      "citationCount": 0,
      "citationDensityPer1000Words": 0,
      "unresolved": [
        "[SOURCE NEEDED for specific regulations]",
        "[SOURCE NEEDED for specific CFIA guidelines]",
        "[SOURCE NEEDED for industry margin benchmarks]"
      ],
      "unknown": [],
      "sourceIds": [],
      "categories": [],
      "score": 32
    },
    {
      "file": "blog/html/article-html-05-ai-automation-small-business.html",
      "words": 8201,
      "citationCount": 0,
      "citationDensityPer1000Words": 0,
      "unresolved": [
        "[SOURCE NEEDED]",
        "[SOURCE NEEDED]",
        "[SOURCE NEEDED]",
        "[SOURCE NEEDED]",
        "[SOURCE NEEDED]",
        "[SOURCE NEEDED]",
        "[SOURCE NEEDED]",
        "[SOURCE NEEDED — verify current Canadian AI and privacy regulation requirements]",
        "[SOURCE NEEDED]",
        "[SOURCE NEEDED — verify current legislative status]",
        "[SOURCE NEEDED]"
      ],
      "unknown": [],
      "sourceIds": [],
      "categories": [],
      "score": 0
    },
    {
      "file": "blog/html/article-html-06-ai-operating-systems-entrepreneurs.html",
      "words": 7913,
      "citationCount": 0,
      "citationDensityPer1000Words": 0,
      "unresolved": [
        "[SOURCE NEEDED]",
        "[SOURCE NEEDED — verify current Canadian AI regulatory requirements with legal counsel]"
      ],
      "unknown": [],
      "sourceIds": [],
      "categories": [],
      "score": 47
    },
    {
      "file": "blog/html/article-html-07-zylx-ai-case-study.html",
      "words": 5815,
      "citationCount": 0,
      "citationDensityPer1000Words": 0,
      "unresolved": [],
      "unknown": [],
      "sourceIds": [],
      "categories": [],
      "score": 77
    }
  ]
}